{"errors":[],"warnings":[],"namedChunkGroups":{"app":{"chunks":[6,1,0,2],"assets":["webpack-runtime-ea1e308950731905cb7a.js","webpack-runtime-ea1e308950731905cb7a.js.map","styles.6dd66b54eb54d38b80dd.css","styles-fd35df5d68f69b05a2d3.js","styles-fd35df5d68f69b05a2d3.js.map","commons-96f24313755b6a78f848.js","commons-96f24313755b6a78f848.js.map","app-c52d5d93602442b4c5cd.js","app-c52d5d93602442b4c5cd.js.map"],"children":{},"childAssets":{}},"component---src-pages-404-js":{"chunks":[1,0,3],"assets":["styles.6dd66b54eb54d38b80dd.css","styles-fd35df5d68f69b05a2d3.js","styles-fd35df5d68f69b05a2d3.js.map","commons-96f24313755b6a78f848.js","commons-96f24313755b6a78f848.js.map","component---src-pages-404-js-de147e2a411283ceee16.js","component---src-pages-404-js-de147e2a411283ceee16.js.map"],"children":{},"childAssets":{}},"component---src-pages-index-js":{"chunks":[1,0,4],"assets":["styles.6dd66b54eb54d38b80dd.css","styles-fd35df5d68f69b05a2d3.js","styles-fd35df5d68f69b05a2d3.js.map","commons-96f24313755b6a78f848.js","commons-96f24313755b6a78f848.js.map","component---src-pages-index-js-612d6a9dc8d6b33ee978.js","component---src-pages-index-js-612d6a9dc8d6b33ee978.js.map"],"children":{},"childAssets":{}},"component---src-pages-page-2-js":{"chunks":[1,0,5],"assets":["styles.6dd66b54eb54d38b80dd.css","styles-fd35df5d68f69b05a2d3.js","styles-fd35df5d68f69b05a2d3.js.map","commons-96f24313755b6a78f848.js","commons-96f24313755b6a78f848.js.map","component---src-pages-page-2-js-186050ffe135cc98d138.js","component---src-pages-page-2-js-186050ffe135cc98d138.js.map"],"children":{},"childAssets":{}}},"assetsByChunkName":{"app":["webpack-runtime-ea1e308950731905cb7a.js","styles.6dd66b54eb54d38b80dd.css","styles-fd35df5d68f69b05a2d3.js","commons-96f24313755b6a78f848.js","app-c52d5d93602442b4c5cd.js"],"component---src-pages-404-js":["styles.6dd66b54eb54d38b80dd.css","styles-fd35df5d68f69b05a2d3.js","commons-96f24313755b6a78f848.js","component---src-pages-404-js-de147e2a411283ceee16.js"],"component---src-pages-index-js":["styles.6dd66b54eb54d38b80dd.css","styles-fd35df5d68f69b05a2d3.js","commons-96f24313755b6a78f848.js","component---src-pages-index-js-612d6a9dc8d6b33ee978.js"],"component---src-pages-page-2-js":["styles.6dd66b54eb54d38b80dd.css","styles-fd35df5d68f69b05a2d3.js","commons-96f24313755b6a78f848.js","component---src-pages-page-2-js-186050ffe135cc98d138.js"]}}